{
  "#92733529-f141-4acb-b85f-2e7c9d3b07b3": {
    "type": "Annotation",
    "body": [
      {
        "type": "TextualBody",
        "purpose": "Transliteration",
        "value": "a",
        "source": "http://purl.org/cuneiform/Transliteration"
      },
      {
        "type": "TextualBody",
        "value": "Character",
        "purpose": "classifying",
        "source": "http://purl.org/cuneiform/Character"
      },
      {
        "type": "TextualBody",
        "purpose": "Line",
        "value": "8",
        "source": "http://purl.org/cuneiform/Line"
      },
      {
        "type": "TextualBody",
        "purpose": "Charindex",
        "value": "2",
        "source": "http://purl.org/cuneiform/CharacterIndex"
      },
      {
        "type": "TextualBody",
        "purpose": "linking",
        "value": "http://cdli.ucla.edu/P358144_char_-1_8_2"
      }
    ],
    "target": {
      "source": "https://heidicon.ub.uni-heidelberg.de/iiif/2/1123403:587713/full/full/0/default.jpg",
      "selector": {
        "type": "SvgSelector",
        "value": "<svg><polygon points=\"76.96875,150.5515594482422 130.8468780517578,146.703125 116.7359390258789,228.80313110351562 66.70625305175781,227.5203094482422\"></polygon></svg>"
      },
      "rights": "https://creativecommons.org/licenses/by-sa/4.0/",
      "dimensions": {
        "x": 821,
        "y": 473
      }
    },
    "@context": "http://www.w3.org/ns/anno.jsonld",
    "id": "#92733529-f141-4acb-b85f-2e7c9d3b07b3",
    "creator": {
      "id": "https://orcid.org/0000-0002-9499-5840",
      "type": "Person",
      "name": "Timo Homburg",
      "nickname": "situx"
    },
    "generator": {
      "id": "https://github.com/recogito/annotorious-openseadragon",
      "type": "Software",
      "name": "Annotorious-OpenSeadragon 1.5.6",
      "homepage": "https://github.com/recogito/annotorious-openseadragon"
    },
    "rights": "https://creativecommons.org/publicdomain/zero/1.0/"
  },
  "#1a245f92-8a0f-49e4-b743-dc6cdff02ed5": {
    "type": "Annotation",
    "body": [
      {
        "type": "TextualBody",
        "purpose": "Transliteration",
        "value": "2/3(disz)",
        "source": "http://purl.org/cuneiform/Transliteration"
      },
      {
        "type": "TextualBody",
        "value": "Character",
        "purpose": "classifying",
        "source": "http://purl.org/cuneiform/Character"
      },
      {
        "type": "TextualBody",
        "purpose": "Line",
        "value": "9",
        "source": "http://purl.org/cuneiform/Line"
      },
      {
        "type": "TextualBody",
        "purpose": "Charindex",
        "value": "2",
        "source": "http://purl.org/cuneiform/CharacterIndex"
      },
      {
        "type": "TextualBody",
        "purpose": "linking",
        "value": "http://cdli.ucla.edu/P358144_char_-1_9_2"
      }
    ],
    "target": {
      "source": "https://heidicon.ub.uni-heidelberg.de/iiif/2/1123403:587713/full/full/0/default.jpg",
      "selector": {
        "type": "SvgSelector",
        "value": "<svg><polygon points=\"144.9578094482422,228.80313110351562 59.009376525878906,226.2375030517578 48.74687576293945,314.7515563964844 126.9984359741211,314.7515563964844\"></polygon></svg>"
      },
      "rights": "https://creativecommons.org/licenses/by-sa/4.0/",
      "dimensions": {
        "x": 821,
        "y": 473
      }
    },
    "@context": "http://www.w3.org/ns/anno.jsonld",
    "id": "#1a245f92-8a0f-49e4-b743-dc6cdff02ed5",
    "creator": {
      "id": "https://orcid.org/0000-0002-9499-5840",
      "type": "Person",
      "name": "Timo Homburg",
      "nickname": "situx"
    },
    "generator": {
      "id": "https://github.com/recogito/annotorious-openseadragon",
      "type": "Software",
      "name": "Annotorious-OpenSeadragon 1.5.6",
      "homepage": "https://github.com/recogito/annotorious-openseadragon"
    },
    "rights": "https://creativecommons.org/publicdomain/zero/1.0/"
  },
  "#cea434bd-23fb-46e9-b881-4f4d3c6385a9": {
    "type": "Annotation",
    "body": [
      {
        "type": "TextualBody",
        "purpose": "Transliteration",
        "value": "ma",
        "source": "http://purl.org/cuneiform/Transliteration"
      },
      {
        "type": "TextualBody",
        "value": "Character",
        "purpose": "classifying",
        "source": "http://purl.org/cuneiform/Character"
      },
      {
        "type": "TextualBody",
        "purpose": "Line",
        "value": "9",
        "source": "http://purl.org/cuneiform/Line"
      },
      {
        "type": "TextualBody",
        "purpose": "Charindex",
        "value": "3",
        "source": "http://purl.org/cuneiform/CharacterIndex"
      },
      {
        "type": "TextualBody",
        "purpose": "linking",
        "value": "http://cdli.ucla.edu/P358144_char_-1_9_3"
      }
    ],
    "target": {
      "source": "https://heidicon.ub.uni-heidelberg.de/iiif/2/1123403:587713/full/full/0/default.jpg",
      "selector": {
        "type": "SvgSelector",
        "value": "<svg><polygon points=\"251.43125915527344,233.9343719482422 143.6750030517578,224.95468139648438 129.56405639648438,308.3374938964844 242.45156860351562,309.62030029296875\"></polygon></svg>"
      },
      "rights": "https://creativecommons.org/licenses/by-sa/4.0/",
      "dimensions": {
        "x": 821,
        "y": 473
      }
    },
    "@context": "http://www.w3.org/ns/anno.jsonld",
    "id": "#cea434bd-23fb-46e9-b881-4f4d3c6385a9",
    "creator": {
      "id": "https://orcid.org/0000-0002-9499-5840",
      "type": "Person",
      "name": "Timo Homburg",
      "nickname": "situx"
    },
    "generator": {
      "id": "https://github.com/recogito/annotorious-openseadragon",
      "type": "Software",
      "name": "Annotorious-OpenSeadragon 1.5.6",
      "homepage": "https://github.com/recogito/annotorious-openseadragon"
    },
    "rights": "https://creativecommons.org/publicdomain/zero/1.0/"
  },
  "#d3c2345c-be8c-43d7-ba56-1d5e982ac6e9": {
    "type": "Annotation",
    "body": [
      {
        "type": "TextualBody",
        "purpose": "Transliteration",
        "value": "na",
        "source": "http://purl.org/cuneiform/Transliteration"
      },
      {
        "type": "TextualBody",
        "value": "Character",
        "purpose": "classifying",
        "source": "http://purl.org/cuneiform/Character"
      },
      {
        "type": "TextualBody",
        "purpose": "Line",
        "value": "9",
        "source": "http://purl.org/cuneiform/Line"
      },
      {
        "type": "TextualBody",
        "purpose": "Charindex",
        "value": "4",
        "source": "http://purl.org/cuneiform/CharacterIndex"
      },
      {
        "type": "TextualBody",
        "purpose": "linking",
        "value": "http://cdli.ucla.edu/P358144_char_-1_9_4"
      }
    ],
    "target": {
      "source": "https://heidicon.ub.uni-heidelberg.de/iiif/2/1123403:587713/full/full/0/default.jpg",
      "selector": {
        "type": "SvgSelector",
        "value": "<svg><polygon points=\"369.45001220703125,226.2375030517578 255.27969360351562,227.5203094482422 246.3000030517578,312.1859436035156 361.7531433105469,316.03436279296875\"></polygon></svg>"
      },
      "rights": "https://creativecommons.org/licenses/by-sa/4.0/",
      "dimensions": {
        "x": 821,
        "y": 473
      }
    },
    "@context": "http://www.w3.org/ns/anno.jsonld",
    "id": "#d3c2345c-be8c-43d7-ba56-1d5e982ac6e9",
    "creator": {
      "id": "https://orcid.org/0000-0002-9499-5840",
      "type": "Person",
      "name": "Timo Homburg",
      "nickname": "situx"
    },
    "generator": {
      "id": "https://github.com/recogito/annotorious-openseadragon",
      "type": "Software",
      "name": "Annotorious-OpenSeadragon 1.5.6",
      "homepage": "https://github.com/recogito/annotorious-openseadragon"
    },
    "rights": "https://creativecommons.org/publicdomain/zero/1.0/"
  },
  "#b7e68901-9c75-47b3-a2c3-6ae4899f8de5": {
    "type": "Annotation",
    "body": [
      {
        "type": "TextualBody",
        "purpose": "Transliteration",
        "value": "uruda",
        "source": "http://purl.org/cuneiform/Transliteration"
      },
      {
        "type": "TextualBody",
        "value": "Character",
        "purpose": "classifying",
        "source": "http://purl.org/cuneiform/Character"
      },
      {
        "type": "TextualBody",
        "purpose": "Line",
        "value": "9",
        "source": "http://purl.org/cuneiform/Line"
      },
      {
        "type": "TextualBody",
        "purpose": "Charindex",
        "value": "5",
        "source": "http://purl.org/cuneiform/CharacterIndex"
      },
      {
        "type": "TextualBody",
        "purpose": "linking",
        "value": "http://cdli.ucla.edu/P358144_char_-1_9_5"
      }
    ],
    "target": {
      "source": "https://heidicon.ub.uni-heidelberg.de/iiif/2/1123403:587713/full/full/0/default.jpg",
      "selector": {
        "type": "SvgSelector",
        "value": "<svg><polygon points=\"495.1656188964844,224.95468139648438 370.7328186035156,221.1062469482422 361.7531433105469,313.46875 493.8828125,309.62030029296875\"></polygon></svg>"
      },
      "rights": "https://creativecommons.org/licenses/by-sa/4.0/",
      "dimensions": {
        "x": 821,
        "y": 473
      }
    },
    "@context": "http://www.w3.org/ns/anno.jsonld",
    "id": "#b7e68901-9c75-47b3-a2c3-6ae4899f8de5",
    "creator": {
      "id": "https://orcid.org/0000-0002-9499-5840",
      "type": "Person",
      "name": "Timo Homburg",
      "nickname": "situx"
    },
    "generator": {
      "id": "https://github.com/recogito/annotorious-openseadragon",
      "type": "Software",
      "name": "Annotorious-OpenSeadragon 1.5.6",
      "homepage": "https://github.com/recogito/annotorious-openseadragon"
    },
    "rights": "https://creativecommons.org/publicdomain/zero/1.0/"
  },
  "#cdef6ec9-bc8e-4f86-a4ca-015a1effbbaa": {
    "type": "Annotation",
    "body": [
      {
        "type": "TextualBody",
        "purpose": "Transliteration",
        "value": "a",
        "source": "http://purl.org/cuneiform/Transliteration"
      },
      {
        "type": "TextualBody",
        "value": "Character",
        "purpose": "classifying",
        "source": "http://purl.org/cuneiform/Character"
      },
      {
        "type": "TextualBody",
        "purpose": "Line",
        "value": "9",
        "source": "http://purl.org/cuneiform/Line"
      },
      {
        "type": "TextualBody",
        "purpose": "Charindex",
        "value": "6",
        "source": "http://purl.org/cuneiform/CharacterIndex"
      },
      {
        "type": "TextualBody",
        "purpose": "linking",
        "value": "http://cdli.ucla.edu/P358144_char_-1_9_6"
      }
    ],
    "target": {
      "source": "https://heidicon.ub.uni-heidelberg.de/iiif/2/1123403:587713/full/full/0/default.jpg",
      "selector": {
        "type": "SvgSelector",
        "value": "<svg><polygon points=\"560.5890502929688,227.5203094482422 499.0140686035156,228.80313110351562 495.1656188964844,308.3374938964844 554.1749877929688,307.0546875\"></polygon></svg>"
      },
      "rights": "https://creativecommons.org/licenses/by-sa/4.0/",
      "dimensions": {
        "x": 821,
        "y": 473
      }
    },
    "@context": "http://www.w3.org/ns/anno.jsonld",
    "id": "#cdef6ec9-bc8e-4f86-a4ca-015a1effbbaa",
    "creator": {
      "id": "https://orcid.org/0000-0002-9499-5840",
      "type": "Person",
      "name": "Timo Homburg",
      "nickname": "situx"
    },
    "generator": {
      "id": "https://github.com/recogito/annotorious-openseadragon",
      "type": "Software",
      "name": "Annotorious-OpenSeadragon 1.5.6",
      "homepage": "https://github.com/recogito/annotorious-openseadragon"
    },
    "rights": "https://creativecommons.org/publicdomain/zero/1.0/"
  },
  "#b3752ccb-03dc-412b-b8b5-44372fa45470": {
    "type": "Annotation",
    "body": [
      {
        "type": "TextualBody",
        "purpose": "Transliteration",
        "value": "na",
        "source": "http://purl.org/cuneiform/Transliteration"
      },
      {
        "type": "TextualBody",
        "value": "Character",
        "purpose": "classifying",
        "source": "http://purl.org/cuneiform/Character"
      },
      {
        "type": "TextualBody",
        "purpose": "Line",
        "value": "9",
        "source": "http://purl.org/cuneiform/Line"
      },
      {
        "type": "TextualBody",
        "purpose": "Charindex",
        "value": "7",
        "source": "http://purl.org/cuneiform/CharacterIndex"
      },
      {
        "type": "TextualBody",
        "purpose": "linking",
        "value": "http://cdli.ucla.edu/P358144_char_-1_9_7"
      }
    ],
    "target": {
      "source": "https://heidicon.ub.uni-heidelberg.de/iiif/2/1123403:587713/full/full/0/default.jpg",
      "selector": {
        "type": "SvgSelector",
        "value": "<svg><polygon points=\"672.1937866210938,222.38906860351562 561.8718872070312,223.671875 559.3062744140625,304.48907470703125 665.7797241210938,305.7718811035156\"></polygon></svg>"
      },
      "rights": "https://creativecommons.org/licenses/by-sa/4.0/",
      "dimensions": {
        "x": 821,
        "y": 473
      }
    },
    "@context": "http://www.w3.org/ns/anno.jsonld",
    "id": "#b3752ccb-03dc-412b-b8b5-44372fa45470",
    "creator": {
      "id": "https://orcid.org/0000-0002-9499-5840",
      "type": "Person",
      "name": "Timo Homburg",
      "nickname": "situx"
    },
    "generator": {
      "id": "https://github.com/recogito/annotorious-openseadragon",
      "type": "Software",
      "name": "Annotorious-OpenSeadragon 1.5.6",
      "homepage": "https://github.com/recogito/annotorious-openseadragon"
    },
    "rights": "https://creativecommons.org/publicdomain/zero/1.0/"
  },
  "#4cbf6b68-afe4-466b-8853-c34d22015487": {
    "type": "Annotation",
    "body": [
      {
        "type": "TextualBody",
        "purpose": "Transliteration",
        "value": "asz2",
        "source": "http://purl.org/cuneiform/Transliteration"
      },
      {
        "type": "TextualBody",
        "value": "Character",
        "purpose": "classifying",
        "source": "http://purl.org/cuneiform/Character"
      },
      {
        "type": "TextualBody",
        "purpose": "Line",
        "value": "10",
        "source": "http://purl.org/cuneiform/Line"
      },
      {
        "type": "TextualBody",
        "purpose": "Charindex",
        "value": "1",
        "source": "http://purl.org/cuneiform/CharacterIndex"
      },
      {
        "type": "TextualBody",
        "purpose": "linking",
        "value": "http://cdli.ucla.edu/P358144_char_-1_10_1"
      }
    ],
    "target": {
      "source": "https://heidicon.ub.uni-heidelberg.de/iiif/2/1123403:587713/full/full/0/default.jpg",
      "selector": {
        "type": "SvgSelector",
        "value": "<svg><polygon points=\"43.61562728881836,313.46875 126.9984359741211,317.31719970703125 118.01875305175781,394.28594970703125 35.91875076293945,391.7203063964844\"></polygon></svg>"
      },
      "rights": "https://creativecommons.org/licenses/by-sa/4.0/",
      "dimensions": {
        "x": 821,
        "y": 473
      }
    },
    "@context": "http://www.w3.org/ns/anno.jsonld",
    "id": "#4cbf6b68-afe4-466b-8853-c34d22015487",
    "creator": {
      "id": "https://orcid.org/0000-0002-9499-5840",
      "type": "Person",
      "name": "Timo Homburg",
      "nickname": "situx"
    },
    "generator": {
      "id": "https://github.com/recogito/annotorious-openseadragon",
      "type": "Software",
      "name": "Annotorious-OpenSeadragon 1.5.6",
      "homepage": "https://github.com/recogito/annotorious-openseadragon"
    },
    "rights": "https://creativecommons.org/publicdomain/zero/1.0/"
  },
  "#b58d9c0d-7b6c-41d5-8503-241518c439bc": {
    "type": "Annotation",
    "body": [
      {
        "type": "TextualBody",
        "purpose": "Transliteration",
        "value": "qu2",
        "source": "http://purl.org/cuneiform/Transliteration"
      },
      {
        "type": "TextualBody",
        "value": "Character",
        "purpose": "classifying",
        "source": "http://purl.org/cuneiform/Character"
      },
      {
        "type": "TextualBody",
        "purpose": "Line",
        "value": "10",
        "source": "http://purl.org/cuneiform/Line"
      },
      {
        "type": "TextualBody",
        "purpose": "Charindex",
        "value": "2",
        "source": "http://purl.org/cuneiform/CharacterIndex"
      },
      {
        "type": "TextualBody",
        "purpose": "linking",
        "value": "http://cdli.ucla.edu/P358144_char_-1_10_2"
      }
    ],
    "target": {
      "source": "https://heidicon.ub.uni-heidelberg.de/iiif/2/1123403:587713/full/full/0/default.jpg",
      "selector": {
        "type": "SvgSelector",
        "value": "<svg><polygon points=\"205.25,314.7515563964844 125.71562957763672,305.7718811035156 116.7359390258789,391.7203063964844 192.421875,391.7203063964844\"></polygon></svg>"
      },
      "rights": "https://creativecommons.org/licenses/by-sa/4.0/",
      "dimensions": {
        "x": 821,
        "y": 473
      }
    },
    "@context": "http://www.w3.org/ns/anno.jsonld",
    "id": "#b58d9c0d-7b6c-41d5-8503-241518c439bc",
    "creator": {
      "id": "https://orcid.org/0000-0002-9499-5840",
      "type": "Person",
      "name": "Timo Homburg",
      "nickname": "situx"
    },
    "generator": {
      "id": "https://github.com/recogito/annotorious-openseadragon",
      "type": "Software",
      "name": "Annotorious-OpenSeadragon 1.5.6",
      "homepage": "https://github.com/recogito/annotorious-openseadragon"
    },
    "rights": "https://creativecommons.org/publicdomain/zero/1.0/"
  },
  "#d5482215-97d8-4520-ba53-7e07bc2b327c": {
    "type": "Annotation",
    "body": [
      {
        "type": "TextualBody",
        "purpose": "Transliteration",
        "value": "ul",
        "source": "http://purl.org/cuneiform/Transliteration"
      },
      {
        "type": "TextualBody",
        "value": "Character",
        "purpose": "classifying",
        "source": "http://purl.org/cuneiform/Character"
      },
      {
        "type": "TextualBody",
        "purpose": "Line",
        "value": "10",
        "source": "http://purl.org/cuneiform/Line"
      },
      {
        "type": "TextualBody",
        "purpose": "Charindex",
        "value": "3",
        "source": "http://purl.org/cuneiform/CharacterIndex"
      },
      {
        "type": "TextualBody",
        "purpose": "linking",
        "value": "http://cdli.ucla.edu/P358144_char_-1_10_3"
      }
    ],
    "target": {
      "source": "https://heidicon.ub.uni-heidelberg.de/iiif/2/1123403:587713/full/full/0/default.jpg",
      "selector": {
        "type": "SvgSelector",
        "value": "<svg><polygon points=\"355.3390808105469,317.31719970703125 209.0984344482422,305.7718811035156 192.421875,395.5687561035156 338.6625061035156,399.41717529296875\"></polygon></svg>"
      },
      "rights": "https://creativecommons.org/licenses/by-sa/4.0/",
      "dimensions": {
        "x": 821,
        "y": 473
      }
    },
    "@context": "http://www.w3.org/ns/anno.jsonld",
    "id": "#d5482215-97d8-4520-ba53-7e07bc2b327c",
    "creator": {
      "id": "https://orcid.org/0000-0002-9499-5840",
      "type": "Person",
      "name": "Timo Homburg",
      "nickname": "situx"
    },
    "generator": {
      "id": "https://github.com/recogito/annotorious-openseadragon",
      "type": "Software",
      "name": "Annotorious-OpenSeadragon 1.5.6",
      "homepage": "https://github.com/recogito/annotorious-openseadragon"
    },
    "rights": "https://creativecommons.org/publicdomain/zero/1.0/"
  },
  "#c5601e24-23e5-484c-9661-2adab922bac9": {
    "type": "Annotation",
    "body": [
      {
        "type": "TextualBody",
        "purpose": "Transliteration",
        "value": "4(disz)",
        "source": "http://purl.org/cuneiform/Transliteration"
      },
      {
        "type": "TextualBody",
        "value": "Character",
        "purpose": "classifying",
        "source": "http://purl.org/cuneiform/Character"
      },
      {
        "type": "TextualBody",
        "purpose": "Line",
        "value": "10",
        "source": "http://purl.org/cuneiform/Line"
      },
      {
        "type": "TextualBody",
        "purpose": "Charindex",
        "value": "4",
        "source": "http://purl.org/cuneiform/CharacterIndex"
      },
      {
        "type": "TextualBody",
        "purpose": "linking",
        "value": "http://cdli.ucla.edu/P358144_char_-1_10_4"
      }
    ],
    "target": {
      "source": "https://heidicon.ub.uni-heidelberg.de/iiif/2/1123403:587713/full/full/0/default.jpg",
      "selector": {
        "type": "SvgSelector",
        "value": "<svg><polygon points=\"418.1968688964844,314.7515563964844 351.4906311035156,312.1859436035156 337.37969970703125,398.1343688964844 411.7828063964844,399.41717529296875\"></polygon></svg>"
      },
      "rights": "https://creativecommons.org/licenses/by-sa/4.0/",
      "dimensions": {
        "x": 821,
        "y": 473
      }
    },
    "@context": "http://www.w3.org/ns/anno.jsonld",
    "id": "#c5601e24-23e5-484c-9661-2adab922bac9",
    "creator": {
      "id": "https://orcid.org/0000-0002-9499-5840",
      "type": "Person",
      "name": "Timo Homburg",
      "nickname": "situx"
    },
    "generator": {
      "id": "https://github.com/recogito/annotorious-openseadragon",
      "type": "Software",
      "name": "Annotorious-OpenSeadragon 1.5.6",
      "homepage": "https://github.com/recogito/annotorious-openseadragon"
    },
    "rights": "https://creativecommons.org/publicdomain/zero/1.0/"
  },
  "#d688bb4d-ff67-43b6-a80a-3cd87244789a": {
    "type": "Annotation",
    "body": [
      {
        "type": "TextualBody",
        "purpose": "Transliteration",
        "value": "sila3",
        "source": "http://purl.org/cuneiform/Transliteration"
      },
      {
        "type": "TextualBody",
        "value": "Character",
        "purpose": "classifying",
        "source": "http://purl.org/cuneiform/Character"
      },
      {
        "type": "TextualBody",
        "purpose": "Line",
        "value": "10",
        "source": "http://purl.org/cuneiform/Line"
      },
      {
        "type": "TextualBody",
        "purpose": "Charindex",
        "value": "5",
        "source": "http://purl.org/cuneiform/CharacterIndex"
      },
      {
        "type": "TextualBody",
        "purpose": "linking",
        "value": "http://cdli.ucla.edu/P358144_char_-1_10_5"
      }
    ],
    "target": {
      "source": "https://heidicon.ub.uni-heidelberg.de/iiif/2/1123403:587713/full/full/0/default.jpg",
      "selector": {
        "type": "SvgSelector",
        "value": "<svg><polygon points=\"534.9328002929688,310.90313720703125 419.4797058105469,308.3374938964844 411.7828063964844,394.28594970703125 519.5390625,387.87188720703125\"></polygon></svg>"
      },
      "rights": "https://creativecommons.org/licenses/by-sa/4.0/",
      "dimensions": {
        "x": 821,
        "y": 473
      }
    },
    "@context": "http://www.w3.org/ns/anno.jsonld",
    "id": "#d688bb4d-ff67-43b6-a80a-3cd87244789a",
    "creator": {
      "id": "https://orcid.org/0000-0002-9499-5840",
      "type": "Person",
      "name": "Timo Homburg",
      "nickname": "situx"
    },
    "generator": {
      "id": "https://github.com/recogito/annotorious-openseadragon",
      "type": "Software",
      "name": "Annotorious-OpenSeadragon 1.5.6",
      "homepage": "https://github.com/recogito/annotorious-openseadragon"
    },
    "rights": "https://creativecommons.org/publicdomain/zero/1.0/"
  },
  "#2ef5f83e-e3ce-4c28-ad43-5d2e6b243608": {
    "type": "Annotation",
    "body": [
      {
        "type": "TextualBody",
        "purpose": "Transliteration",
        "value": "ka",
        "source": "http://purl.org/cuneiform/Transliteration"
      },
      {
        "type": "TextualBody",
        "value": "Character",
        "purpose": "classifying",
        "source": "http://purl.org/cuneiform/Character"
      },
      {
        "type": "TextualBody",
        "purpose": "Line",
        "value": "10",
        "source": "http://purl.org/cuneiform/Line"
      },
      {
        "type": "TextualBody",
        "purpose": "Charindex",
        "value": "6",
        "source": "http://purl.org/cuneiform/CharacterIndex"
      },
      {
        "type": "TextualBody",
        "purpose": "linking",
        "value": "http://cdli.ucla.edu/P358144_char_-1_10_6"
      }
    ],
    "target": {
      "source": "https://heidicon.ub.uni-heidelberg.de/iiif/2/1123403:587713/full/full/0/default.jpg",
      "selector": {
        "type": "SvgSelector",
        "value": "<svg><polygon points=\"645.2546997070312,309.62030029296875 536.2156372070312,307.0546875 522.1046752929688,381.45782470703125 637.5578002929688,381.45782470703125\"></polygon></svg>"
      },
      "rights": "https://creativecommons.org/licenses/by-sa/4.0/",
      "dimensions": {
        "x": 821,
        "y": 473
      }
    },
    "@context": "http://www.w3.org/ns/anno.jsonld",
    "id": "#2ef5f83e-e3ce-4c28-ad43-5d2e6b243608",
    "creator": {
      "id": "https://orcid.org/0000-0002-9499-5840",
      "type": "Person",
      "name": "Timo Homburg",
      "nickname": "situx"
    },
    "generator": {
      "id": "https://github.com/recogito/annotorious-openseadragon",
      "type": "Software",
      "name": "Annotorious-OpenSeadragon 1.5.6",
      "homepage": "https://github.com/recogito/annotorious-openseadragon"
    },
    "rights": "https://creativecommons.org/publicdomain/zero/1.0/"
  },
  "#ebc343ec-cf33-453d-9b54-43dfe5b4ff43": {
    "type": "Annotation",
    "body": [
      {
        "type": "TextualBody",
        "purpose": "Transliteration",
        "value": "i",
        "source": "http://purl.org/cuneiform/Transliteration"
      },
      {
        "type": "TextualBody",
        "value": "Character",
        "purpose": "classifying",
        "source": "http://purl.org/cuneiform/Character"
      },
      {
        "type": "TextualBody",
        "purpose": "Line",
        "value": "7",
        "source": "http://purl.org/cuneiform/Line"
      },
      {
        "type": "TextualBody",
        "purpose": "Charindex",
        "value": "2",
        "source": "http://purl.org/cuneiform/CharacterIndex"
      },
      {
        "type": "TextualBody",
        "purpose": "linking",
        "value": "http://cdli.ucla.edu/P358144_char_-1_7_2"
      }
    ],
    "target": {
      "source": "https://heidicon.ub.uni-heidelberg.de/iiif/2/1123403:587713/full/full/0/default.jpg",
      "selector": {
        "type": "SvgSelector",
        "value": "<svg><polygon points=\"183.4421844482422,85.12812805175781 107.7562484741211,83.8453140258789 96.2109375,147.98593139648438 182.1593780517578,151.83438110351562\"></polygon></svg>"
      },
      "rights": "https://creativecommons.org/licenses/by-sa/4.0/",
      "dimensions": {
        "x": 821,
        "y": 473
      }
    },
    "@context": "http://www.w3.org/ns/anno.jsonld",
    "id": "#ebc343ec-cf33-453d-9b54-43dfe5b4ff43",
    "creator": {
      "id": "https://orcid.org/0000-0002-9499-5840",
      "type": "Person",
      "name": "Timo Homburg",
      "nickname": "situx"
    },
    "generator": {
      "id": "https://github.com/recogito/annotorious-openseadragon",
      "type": "Software",
      "name": "Annotorious-OpenSeadragon 1.5.6",
      "homepage": "https://github.com/recogito/annotorious-openseadragon"
    },
    "rights": "https://creativecommons.org/publicdomain/zero/1.0/"
  },
  "#a5231690-27cc-4f05-b4dc-bb315058fddc": {
    "type": "Annotation",
    "body": [
      {
        "type": "TextualBody",
        "purpose": "Transliteration",
        "value": "im",
        "source": "http://purl.org/cuneiform/Transliteration"
      },
      {
        "type": "TextualBody",
        "value": "Character",
        "purpose": "classifying",
        "source": "http://purl.org/cuneiform/Character"
      },
      {
        "type": "TextualBody",
        "purpose": "Line",
        "value": "7",
        "source": "http://purl.org/cuneiform/Line"
      },
      {
        "type": "TextualBody",
        "purpose": "Charindex",
        "value": "3",
        "source": "http://purl.org/cuneiform/CharacterIndex"
      },
      {
        "type": "TextualBody",
        "purpose": "linking",
        "value": "http://cdli.ucla.edu/P358144_char_-1_7_3"
      }
    ],
    "target": {
      "source": "https://heidicon.ub.uni-heidelberg.de/iiif/2/1123403:587713/full/full/0/default.jpg",
      "selector": {
        "type": "SvgSelector",
        "value": "<svg><polygon points=\"329.6828308105469,69.734375 192.421875,68.4515609741211 184.72500610351562,146.703125 321.9859313964844,150.5515594482422\"></polygon></svg>"
      },
      "rights": "https://creativecommons.org/licenses/by-sa/4.0/",
      "dimensions": {
        "x": 821,
        "y": 473
      }
    },
    "@context": "http://www.w3.org/ns/anno.jsonld",
    "id": "#a5231690-27cc-4f05-b4dc-bb315058fddc",
    "creator": {
      "id": "https://orcid.org/0000-0002-9499-5840",
      "type": "Person",
      "name": "Timo Homburg",
      "nickname": "situx"
    },
    "generator": {
      "id": "https://github.com/recogito/annotorious-openseadragon",
      "type": "Software",
      "name": "Annotorious-OpenSeadragon 1.5.6",
      "homepage": "https://github.com/recogito/annotorious-openseadragon"
    },
    "rights": "https://creativecommons.org/publicdomain/zero/1.0/"
  }
}