{
  "#76c62d2f-ecbc-4081-8dbd-1395eb99997c": {
    "type": "Annotation",
    "body": [
      {
        "type": "TextualBody",
        "purpose": "Transliteration",
        "value": "7(disz)",
        "source": "http://purl.org/cuneiform/Transliteration"
      },
      {
        "type": "TextualBody",
        "purpose": "Transliteration",
        "value": "7(disz)",
        "source": "http://purl.org/cuneiform/Transliteration"
      },
      {
        "type": "TextualBody",
        "value": "Character",
        "purpose": "classifying",
        "source": "http://purl.org/cuneiform/Character"
      },
      {
        "type": "TextualBody",
        "purpose": "Charindex",
        "value": "2",
        "source": "http://purl.org/cuneiform/CharacterIndex"
      },
      {
        "type": "TextualBody",
        "purpose": "Line",
        "value": "4",
        "source": "http://purl.org/cuneiform/Line"
      },
      {
        "type": "TextualBody",
        "purpose": "Wordindex",
        "value": "2",
        "source": "http://purl.org/cuneiform/WordIndex"
      },
      {
        "type": "TextualBody",
        "purpose": "RelCharindex",
        "value": "0",
        "source": "http://purl.org/cuneiform/RelativeCharacterIndex"
      },
      {
        "type": "TextualBody",
        "purpose": "linking",
        "value": "http://cdli.ucla.edu/P134535_char_-1_4_2"
      }
    ],
    "target": {
      "source": "https://heidicon.ub.uni-heidelberg.de/iiif/2/1113833:577980/full/full/0/default.jpg",
      "selector": {
        "type": "SvgSelector",
        "value": "<svg><polygon points=\"223.44827270507812,386.4413757324219 368.193115234375,383.7103576660156 347.7103576660156,520.2620849609375 219.3517303466797,527.0896606445312\"></polygon></svg>"
      },
      "rights": "https://creativecommons.org/licenses/by-sa/4.0/",
      "dimensions": {
        "x": 720,
        "y": 792
      }
    },
    "@context": "http://www.w3.org/ns/anno.jsonld",
    "id": "#76c62d2f-ecbc-4081-8dbd-1395eb99997c",
    "rights": "https://creativecommons.org/publicdomain/zero/1.0/",
    "creator": {
      "id": "https://orcid.org/0000-0002-9499-5840",
      "type": "Person",
      "name": "Timo Homburg",
      "nickname": "situx"
    },
    "generator": {
      "id": "https://github.com/recogito/annotorious-openseadragon",
      "type": "Software",
      "name": "Annotorious-OpenSeadragon 1.5.6",
      "homepage": "https://github.com/recogito/annotorious-openseadragon"
    }
  },
  "#560b2932-a514-42e1-a1ce-b1a025964caa": {
    "type": "Annotation",
    "body": [
      {
        "type": "TextualBody",
        "purpose": "Transliteration",
        "value": "b",
        "source": "http://purl.org/cuneiform/Transliteration"
      },
      {
        "type": "TextualBody",
        "purpose": "Transliteration",
        "value": "ba",
        "source": "http://purl.org/cuneiform/Transliteration"
      },
      {
        "type": "TextualBody",
        "value": "Character",
        "purpose": "classifying",
        "source": "http://purl.org/cuneiform/Character"
      },
      {
        "type": "TextualBody",
        "purpose": "Line",
        "value": "4",
        "source": "http://purl.org/cuneiform/Line"
      },
      {
        "type": "TextualBody",
        "purpose": "Charindex",
        "value": "3",
        "source": "http://purl.org/cuneiform/CharacterIndex"
      },
      {
        "type": "TextualBody",
        "purpose": "Wordindex",
        "value": "3",
        "source": "http://purl.org/cuneiform/WordIndex"
      },
      {
        "type": "TextualBody",
        "purpose": "RelCharindex",
        "value": "0",
        "source": "http://purl.org/cuneiform/RelativeCharacterIndex"
      },
      {
        "type": "TextualBody",
        "purpose": "linking",
        "value": "http://cdli.ucla.edu/P134535_char_-1_4_3"
      }
    ],
    "target": {
      "source": "https://heidicon.ub.uni-heidelberg.de/iiif/2/1113833:577980/full/full/0/default.jpg",
      "selector": {
        "type": "SvgSelector",
        "value": "<svg><polygon points=\"391.4068908691406,370.05517578125 523.862060546875,363.22760009765625 518.4000244140625,501.14483642578125 398.2344970703125,503.8758544921875\"></polygon></svg>"
      },
      "rights": "https://creativecommons.org/licenses/by-sa/4.0/",
      "dimensions": {
        "x": 720,
        "y": 792
      }
    },
    "@context": "http://www.w3.org/ns/anno.jsonld",
    "id": "#560b2932-a514-42e1-a1ce-b1a025964caa",
    "rights": "https://creativecommons.org/publicdomain/zero/1.0/",
    "creator": {
      "id": "https://orcid.org/0000-0002-9499-5840",
      "type": "Person",
      "name": "Timo Homburg",
      "nickname": "situx"
    },
    "generator": {
      "id": "https://github.com/recogito/annotorious-openseadragon",
      "type": "Software",
      "name": "Annotorious-OpenSeadragon 1.5.6",
      "homepage": "https://github.com/recogito/annotorious-openseadragon"
    }
  },
  "#a291a3e9-d887-443d-9a1d-e91e4cbe4cce": {
    "type": "Annotation",
    "body": [
      {
        "type": "TextualBody",
        "purpose": "Transliteration",
        "value": "za",
        "source": "http://purl.org/cuneiform/Transliteration"
      },
      {
        "type": "TextualBody",
        "purpose": "Transliteration",
        "value": "zal",
        "source": "http://purl.org/cuneiform/Transliteration"
      },
      {
        "type": "TextualBody",
        "purpose": "Line",
        "value": "4",
        "source": "http://purl.org/cuneiform/Line"
      },
      {
        "type": "TextualBody",
        "purpose": "Charindex",
        "value": "4",
        "source": "http://purl.org/cuneiform/CharacterIndex"
      },
      {
        "type": "TextualBody",
        "purpose": "Wordindex",
        "value": "3",
        "source": "http://purl.org/cuneiform/WordIndex"
      },
      {
        "type": "TextualBody",
        "purpose": "RelCharindex",
        "value": "1",
        "source": "http://purl.org/cuneiform/RelativeCharacterIndex"
      },
      {
        "type": "TextualBody",
        "purpose": "linking",
        "value": "http://cdli.ucla.edu/P134535_char_-1_4_4"
      }
    ],
    "target": {
      "source": "https://heidicon.ub.uni-heidelberg.de/iiif/2/1113833:577980/full/full/0/default.jpg",
      "selector": {
        "type": "SvgSelector",
        "value": "<svg><polygon points=\"551.1724243164062,365.9586181640625 712.303466796875,359.13104248046875 713.6689453125,468.3724060058594 563.4620971679688,488.85516357421875\"></polygon></svg>"
      },
      "rights": "https://creativecommons.org/licenses/by-sa/4.0/",
      "dimensions": {
        "x": 720,
        "y": 792
      }
    },
    "@context": "http://www.w3.org/ns/anno.jsonld",
    "id": "#a291a3e9-d887-443d-9a1d-e91e4cbe4cce",
    "rights": "https://creativecommons.org/publicdomain/zero/1.0/",
    "creator": {
      "id": "https://orcid.org/0000-0002-9499-5840",
      "type": "Person",
      "name": "Timo Homburg",
      "nickname": "situx"
    },
    "generator": {
      "id": "https://github.com/recogito/annotorious-openseadragon",
      "type": "Software",
      "name": "Annotorious-OpenSeadragon 1.5.6",
      "homepage": "https://github.com/recogito/annotorious-openseadragon"
    }
  },
  "#94ea94cb-cdb4-4a16-9c4a-ae1cb9fe4b71": {
    "type": "Annotation",
    "body": [
      {
        "type": "TextualBody",
        "purpose": "Transliteration",
        "value": "u54",
        "source": "http://purl.org/cuneiform/Transliteration"
      },
      {
        "type": "TextualBody",
        "purpose": "Transliteration",
        "value": "u4",
        "source": "http://purl.org/cuneiform/Transliteration"
      },
      {
        "type": "TextualBody",
        "value": "Character",
        "purpose": "classifying",
        "source": "http://purl.org/cuneiform/Character"
      },
      {
        "type": "TextualBody",
        "purpose": "Charindex",
        "value": "1",
        "source": "http://purl.org/cuneiform/CharacterIndex"
      },
      {
        "type": "TextualBody",
        "purpose": "Line",
        "value": "4",
        "source": "http://purl.org/cuneiform/Line"
      },
      {
        "type": "TextualBody",
        "purpose": "Wordindex",
        "value": "1",
        "source": "http://purl.org/cuneiform/WordIndex"
      },
      {
        "type": "TextualBody",
        "purpose": "RelCharindex",
        "value": "0",
        "source": "http://purl.org/cuneiform/RelativeCharacterIndex"
      },
      {
        "type": "TextualBody",
        "purpose": "linking",
        "value": "http://cdli.ucla.edu/P134535_char_-1_4_1"
      }
    ],
    "target": {
      "source": "https://heidicon.ub.uni-heidelberg.de/iiif/2/1113833:577980/full/full/0/default.jpg",
      "selector": {
        "type": "SvgSelector",
        "value": "<svg><polygon points=\"18.620689392089844,413.7517395019531 152.44137573242188,404.193115234375 145.61380004882812,538.0137939453125 19.986207962036133,548.9379272460938\"></polygon></svg>"
      },
      "rights": "https://creativecommons.org/licenses/by-sa/4.0/",
      "dimensions": {
        "x": 720,
        "y": 792
      }
    },
    "@context": "http://www.w3.org/ns/anno.jsonld",
    "id": "#94ea94cb-cdb4-4a16-9c4a-ae1cb9fe4b71",
    "rights": "https://creativecommons.org/publicdomain/zero/1.0/",
    "creator": {
      "id": "https://orcid.org/0000-0002-9499-5840",
      "type": "Person",
      "name": "Timo Homburg",
      "nickname": "situx"
    },
    "generator": {
      "id": "https://github.com/recogito/annotorious-openseadragon",
      "type": "Software",
      "name": "Annotorious-OpenSeadragon 1.5.6",
      "homepage": "https://github.com/recogito/annotorious-openseadragon"
    }
  },
  "#9b7a753d-7349-4ccc-84b9-d8845d0da011": {
    "type": "Annotation",
    "body": [
      {
        "type": "TextualBody",
        "purpose": "Transliteration",
        "value": "s",
        "source": "http://purl.org/cuneiform/Transliteration"
      },
      {
        "type": "TextualBody",
        "purpose": "Transliteration",
        "value": "su",
        "source": "http://purl.org/cuneiform/Transliteration"
      },
      {
        "type": "TextualBody",
        "value": "Character",
        "purpose": "classifying",
        "source": "http://purl.org/cuneiform/Character"
      },
      {
        "type": "TextualBody",
        "purpose": "Charindex",
        "value": "4",
        "source": "http://purl.org/cuneiform/CharacterIndex"
      },
      {
        "type": "TextualBody",
        "purpose": "Line",
        "value": "3",
        "source": "http://purl.org/cuneiform/Line"
      },
      {
        "type": "TextualBody",
        "purpose": "Wordindex",
        "value": "3",
        "source": "http://purl.org/cuneiform/WordIndex"
      },
      {
        "type": "TextualBody",
        "purpose": "RelCharindex",
        "value": "1",
        "source": "http://purl.org/cuneiform/RelativeCharacterIndex"
      },
      {
        "type": "TextualBody",
        "purpose": "linking",
        "value": "http://cdli.ucla.edu/P134535_char_-1_3_4"
      }
    ],
    "target": {
      "source": "https://heidicon.ub.uni-heidelberg.de/iiif/2/1113833:577980/full/full/0/default.jpg",
      "selector": {
        "type": "SvgSelector",
        "value": "<svg><polygon points=\"564.8275756835938,240.33103942871094 704.1103515625,240.33103942871094 702.7448120117188,341.3793029785156 563.4620971679688,345.4758605957031\"></polygon></svg>"
      },
      "rights": "https://creativecommons.org/licenses/by-sa/4.0/",
      "dimensions": {
        "x": 720,
        "y": 792
      }
    },
    "@context": "http://www.w3.org/ns/anno.jsonld",
    "id": "#9b7a753d-7349-4ccc-84b9-d8845d0da011",
    "rights": "https://creativecommons.org/publicdomain/zero/1.0/",
    "creator": {
      "id": "https://orcid.org/0000-0002-9499-5840",
      "type": "Person",
      "name": "Timo Homburg",
      "nickname": "situx"
    },
    "generator": {
      "id": "https://github.com/recogito/annotorious-openseadragon",
      "type": "Software",
      "name": "Annotorious-OpenSeadragon 1.5.6",
      "homepage": "https://github.com/recogito/annotorious-openseadragon"
    }
  },
  "#7cfeedb4-68a6-4a6f-8ec2-486a91619466": {
    "type": "Annotation",
    "body": [
      {
        "type": "TextualBody",
        "purpose": "Transliteration",
        "value": "s",
        "source": "http://purl.org/cuneiform/Transliteration"
      },
      {
        "type": "TextualBody",
        "purpose": "Transliteration",
        "value": "si",
        "source": "http://purl.org/cuneiform/Transliteration"
      },
      {
        "type": "TextualBody",
        "value": "Character",
        "purpose": "classifying",
        "source": "http://purl.org/cuneiform/Character"
      },
      {
        "type": "TextualBody",
        "purpose": "Line",
        "value": "3",
        "source": "http://purl.org/cuneiform/Line"
      },
      {
        "type": "TextualBody",
        "purpose": "Charindex",
        "value": "3",
        "source": "http://purl.org/cuneiform/CharacterIndex"
      },
      {
        "type": "TextualBody",
        "purpose": "Wordindex",
        "value": "3",
        "source": "http://purl.org/cuneiform/WordIndex"
      },
      {
        "type": "TextualBody",
        "purpose": "RelCharindex",
        "value": "0",
        "source": "http://purl.org/cuneiform/RelativeCharacterIndex"
      },
      {
        "type": "TextualBody",
        "purpose": "linking",
        "value": "http://cdli.ucla.edu/P134535_char_-1_3_3"
      }
    ],
    "target": {
      "source": "https://heidicon.ub.uni-heidelberg.de/iiif/2/1113833:577980/full/full/0/default.jpg",
      "selector": {
        "type": "SvgSelector",
        "value": "<svg><polygon points=\"384.5793151855469,249.88966369628906 530.6896362304688,247.1586151123047 523.862060546875,352.3034362792969 388.6758728027344,356.3999938964844\"></polygon></svg>"
      },
      "rights": "https://creativecommons.org/licenses/by-sa/4.0/",
      "dimensions": {
        "x": 720,
        "y": 792
      }
    },
    "@context": "http://www.w3.org/ns/anno.jsonld",
    "id": "#7cfeedb4-68a6-4a6f-8ec2-486a91619466",
    "rights": "https://creativecommons.org/publicdomain/zero/1.0/",
    "creator": {
      "id": "https://orcid.org/0000-0002-9499-5840",
      "type": "Person",
      "name": "Timo Homburg",
      "nickname": "situx"
    },
    "generator": {
      "id": "https://github.com/recogito/annotorious-openseadragon",
      "type": "Software",
      "name": "Annotorious-OpenSeadragon 1.5.6",
      "homepage": "https://github.com/recogito/annotorious-openseadragon"
    }
  },
  "#8df2e282-9bf6-4aa1-b0bd-8569df87543b": {
    "type": "Annotation",
    "body": [
      {
        "type": "TextualBody",
        "purpose": "Transliteration",
        "value": "gu",
        "source": "http://purl.org/cuneiform/Transliteration"
      },
      {
        "type": "TextualBody",
        "purpose": "Transliteration",
        "value": "gu4",
        "source": "http://purl.org/cuneiform/Transliteration"
      },
      {
        "type": "TextualBody",
        "value": "Character",
        "purpose": "classifying",
        "source": "http://purl.org/cuneiform/Character"
      },
      {
        "type": "TextualBody",
        "purpose": "Line",
        "value": "3",
        "source": "http://purl.org/cuneiform/Line"
      },
      {
        "type": "TextualBody",
        "purpose": "Charindex",
        "value": "2",
        "source": "http://purl.org/cuneiform/CharacterIndex"
      },
      {
        "type": "TextualBody",
        "purpose": "Wordindex",
        "value": "2",
        "source": "http://purl.org/cuneiform/WordIndex"
      },
      {
        "type": "TextualBody",
        "purpose": "RelCharindex",
        "value": "0",
        "source": "http://purl.org/cuneiform/RelativeCharacterIndex"
      },
      {
        "type": "TextualBody",
        "purpose": "linking",
        "value": "http://cdli.ucla.edu/P134535_char_-1_3_2"
      }
    ],
    "target": {
      "source": "https://heidicon.ub.uni-heidelberg.de/iiif/2/1113833:577980/full/full/0/default.jpg",
      "selector": {
        "type": "SvgSelector",
        "value": "<svg><polygon points=\"211.1586151123047,253.9862060546875 360,245.79310607910156 350.4413757324219,376.88275146484375 209.79310607910156,379.6138000488281\"></polygon></svg>"
      },
      "rights": "https://creativecommons.org/licenses/by-sa/4.0/",
      "dimensions": {
        "x": 720,
        "y": 792
      }
    },
    "@context": "http://www.w3.org/ns/anno.jsonld",
    "id": "#8df2e282-9bf6-4aa1-b0bd-8569df87543b",
    "rights": "https://creativecommons.org/publicdomain/zero/1.0/",
    "creator": {
      "id": "https://orcid.org/0000-0002-9499-5840",
      "type": "Person",
      "name": "Timo Homburg",
      "nickname": "situx"
    },
    "generator": {
      "id": "https://github.com/recogito/annotorious-openseadragon",
      "type": "Software",
      "name": "Annotorious-OpenSeadragon 1.5.6",
      "homepage": "https://github.com/recogito/annotorious-openseadragon"
    }
  },
  "#659b9a69-ef33-4d03-8cae-8a5130f87129": {
    "type": "Annotation",
    "body": [
      {
        "type": "TextualBody",
        "purpose": "Transliteration",
        "value": "m",
        "source": "http://purl.org/cuneiform/Transliteration"
      },
      {
        "type": "TextualBody",
        "purpose": "Transliteration",
        "value": "mu",
        "source": "http://purl.org/cuneiform/Transliteration"
      },
      {
        "type": "TextualBody",
        "purpose": "Line",
        "value": "3",
        "source": "http://purl.org/cuneiform/Line"
      },
      {
        "type": "TextualBody",
        "purpose": "Charindex",
        "value": "1",
        "source": "http://purl.org/cuneiform/CharacterIndex"
      },
      {
        "type": "TextualBody",
        "purpose": "Wordindex",
        "value": "1",
        "source": "http://purl.org/cuneiform/WordIndex"
      },
      {
        "type": "TextualBody",
        "purpose": "RelCharindex",
        "value": "0",
        "source": "http://purl.org/cuneiform/RelativeCharacterIndex"
      },
      {
        "type": "TextualBody",
        "purpose": "linking",
        "value": "http://cdli.ucla.edu/P134535_char_-1_3_1"
      }
    ],
    "target": {
      "source": "https://heidicon.ub.uni-heidelberg.de/iiif/2/1113833:577980/full/full/0/default.jpg",
      "selector": {
        "type": "SvgSelector",
        "value": "<svg><polygon points=\"14.51661491394043,279.4520263671875 149.97116088867188,276.7247619628906 139.06207275390625,393.9974670410156 21.789342880249023,404.9065856933594\"></polygon></svg>"
      },
      "rights": "https://creativecommons.org/licenses/by-sa/4.0/",
      "dimensions": {
        "x": 720,
        "y": 792
      }
    },
    "@context": "http://www.w3.org/ns/anno.jsonld",
    "id": "#659b9a69-ef33-4d03-8cae-8a5130f87129",
    "rights": "https://creativecommons.org/publicdomain/zero/1.0/",
    "creator": {
      "id": "https://orcid.org/0000-0002-9499-5840",
      "type": "Person",
      "name": "Timo Homburg",
      "nickname": "situx"
    },
    "generator": {
      "id": "https://github.com/recogito/annotorious-openseadragon",
      "type": "Software",
      "name": "Annotorious-OpenSeadragon 1.5.6",
      "homepage": "https://github.com/recogito/annotorious-openseadragon"
    }
  },
  "#21ba947a-f752-4c65-be12-66529d078933": {
    "type": "Annotation",
    "body": [
      {
        "type": "TextualBody",
        "purpose": "Transliteration",
        "value": "mu",
        "source": "http://purl.org/cuneiform/Transliteration"
      },
      {
        "type": "TextualBody",
        "value": "Character",
        "purpose": "classifying",
        "source": "http://purl.org/cuneiform/Character"
      },
      {
        "type": "TextualBody",
        "purpose": "Charindex",
        "value": "1",
        "source": "http://purl.org/cuneiform/CharacterIndex"
      },
      {
        "type": "TextualBody",
        "purpose": "Line",
        "value": "2",
        "source": "http://purl.org/cuneiform/Line"
      },
      {
        "type": "TextualBody",
        "purpose": "Wordindex",
        "value": "1",
        "source": "http://purl.org/cuneiform/WordIndex"
      },
      {
        "type": "TextualBody",
        "purpose": "RelCharindex",
        "value": "0",
        "source": "http://purl.org/cuneiform/RelativeCharacterIndex"
      },
      {
        "type": "TextualBody",
        "purpose": "linking",
        "value": "http://cdli.ucla.edu/P134535_char_-1_2_1"
      }
    ],
    "target": {
      "source": "https://heidicon.ub.uni-heidelberg.de/iiif/2/1113833:577980/full/full/0/default.jpg",
      "selector": {
        "type": "SvgSelector",
        "value": "<svg><polygon points=\"9.0620698928833,184.34483337402344 198.8689727783203,184.34483337402344 198.8689727783203,279.9310302734375 10.427586555480957,286.7586364746094\"></polygon></svg>"
      },
      "rights": "https://creativecommons.org/licenses/by-sa/4.0/",
      "dimensions": {
        "x": 720,
        "y": 792
      }
    },
    "@context": "http://www.w3.org/ns/anno.jsonld",
    "id": "#21ba947a-f752-4c65-be12-66529d078933",
    "rights": "https://creativecommons.org/publicdomain/zero/1.0/",
    "creator": {
      "id": "https://orcid.org/0000-0002-9499-5840",
      "type": "Person",
      "name": "Timo Homburg",
      "nickname": "situx"
    },
    "generator": {
      "id": "https://github.com/recogito/annotorious-openseadragon",
      "type": "Software",
      "name": "Annotorious-OpenSeadragon 1.5.6",
      "homepage": "https://github.com/recogito/annotorious-openseadragon"
    }
  },
  "#24b4d0bf-ee79-4b96-ba20-f02243440085": {
    "type": "Annotation",
    "body": [
      {
        "type": "TextualBody",
        "purpose": "Transliteration",
        "value": "mu",
        "source": "http://purl.org/cuneiform/Transliteration"
      },
      {
        "type": "TextualBody",
        "value": "Character",
        "purpose": "classifying",
        "source": "http://purl.org/cuneiform/Character"
      },
      {
        "type": "TextualBody",
        "purpose": "Line",
        "value": "5",
        "source": "http://purl.org/cuneiform/Line"
      },
      {
        "type": "TextualBody",
        "purpose": "Charindex",
        "value": "1",
        "source": "http://purl.org/cuneiform/CharacterIndex"
      },
      {
        "type": "TextualBody",
        "purpose": "linking",
        "value": "http://cdli.ucla.edu/P134535_char_-1_5_1"
      }
    ],
    "target": {
      "source": "https://heidicon.ub.uni-heidelberg.de/iiif/2/1113833:577980/full/full/0/default.jpg",
      "selector": {
        "type": "SvgSelector",
        "value": "<svg><polygon points=\"21.35172462463379,557.1310424804688 183.84828186035156,539.3793334960938 182.48275756835938,660.9103393554688 19.986207962036133,665.0068969726562\"></polygon></svg>"
      },
      "rights": "https://creativecommons.org/licenses/by-sa/4.0/",
      "dimensions": {
        "x": 720,
        "y": 792
      }
    },
    "@context": "http://www.w3.org/ns/anno.jsonld",
    "id": "#24b4d0bf-ee79-4b96-ba20-f02243440085",
    "rights": "https://creativecommons.org/publicdomain/zero/1.0/",
    "creator": {
      "id": "https://orcid.org/0000-0002-9499-5840",
      "type": "Person",
      "name": "Timo Homburg",
      "nickname": "situx"
    },
    "generator": {
      "id": "https://github.com/recogito/annotorious-openseadragon",
      "type": "Software",
      "name": "Annotorious-OpenSeadragon 1.5.6",
      "homepage": "https://github.com/recogito/annotorious-openseadragon"
    }
  },
  "#11d739aa-9f0e-41c5-bd89-38f28dcffee2": {
    "type": "Annotation",
    "body": [
      {
        "type": "TextualBody",
        "purpose": "Transliteration",
        "value": "en",
        "source": "http://purl.org/cuneiform/Transliteration"
      },
      {
        "type": "TextualBody",
        "value": "Character",
        "purpose": "classifying",
        "source": "http://purl.org/cuneiform/Character"
      },
      {
        "type": "TextualBody",
        "purpose": "Line",
        "value": "5",
        "source": "http://purl.org/cuneiform/Line"
      },
      {
        "type": "TextualBody",
        "purpose": "Charindex",
        "value": "2",
        "source": "http://purl.org/cuneiform/CharacterIndex"
      },
      {
        "type": "TextualBody",
        "purpose": "linking",
        "value": "http://cdli.ucla.edu/P134535_char_-1_5_2"
      }
    ],
    "target": {
      "source": "https://heidicon.ub.uni-heidelberg.de/iiif/2/1113833:577980/full/full/0/default.jpg",
      "selector": {
        "type": "SvgSelector",
        "value": "<svg><polygon points=\"193.40689086914062,532.5516967773438 396.86895751953125,514.7999877929688 406.4275817871094,647.2551879882812 187.94482421875,648.6206665039062\"></polygon></svg>"
      },
      "rights": "https://creativecommons.org/licenses/by-sa/4.0/",
      "dimensions": {
        "x": 720,
        "y": 792
      }
    },
    "@context": "http://www.w3.org/ns/anno.jsonld",
    "id": "#11d739aa-9f0e-41c5-bd89-38f28dcffee2",
    "rights": "https://creativecommons.org/publicdomain/zero/1.0/",
    "creator": {
      "id": "https://orcid.org/0000-0002-9499-5840",
      "type": "Person",
      "name": "Timo Homburg",
      "nickname": "situx"
    },
    "generator": {
      "id": "https://github.com/recogito/annotorious-openseadragon",
      "type": "Software",
      "name": "Annotorious-OpenSeadragon 1.5.6",
      "homepage": "https://github.com/recogito/annotorious-openseadragon"
    }
  },
  "#fe4da6b7-b702-4a39-81a6-eed5721056b8": {
    "type": "Annotation",
    "body": [
      {
        "type": "TextualBody",
        "purpose": "Transliteration",
        "value": "d",
        "source": "http://purl.org/cuneiform/Transliteration"
      },
      {
        "type": "TextualBody",
        "value": "Character",
        "purpose": "classifying",
        "source": "http://purl.org/cuneiform/Character"
      },
      {
        "type": "TextualBody",
        "purpose": "Line",
        "value": "5",
        "source": "http://purl.org/cuneiform/Line"
      },
      {
        "type": "TextualBody",
        "purpose": "Charindex",
        "value": "3",
        "source": "http://purl.org/cuneiform/CharacterIndex"
      },
      {
        "type": "TextualBody",
        "purpose": "linking",
        "value": "http://cdli.ucla.edu/P134535_char_-1_5_3"
      }
    ],
    "target": {
      "source": "https://heidicon.ub.uni-heidelberg.de/iiif/2/1113833:577980/full/full/0/default.jpg",
      "selector": {
        "type": "SvgSelector",
        "value": "<svg><polygon points=\"399.6000061035156,512.0689697265625 548.44140625,494.3172302246094 553.9034423828125,611.751708984375 409.15863037109375,630.8689575195312\"></polygon></svg>"
      },
      "rights": "https://creativecommons.org/licenses/by-sa/4.0/",
      "dimensions": {
        "x": 720,
        "y": 792
      }
    },
    "@context": "http://www.w3.org/ns/anno.jsonld",
    "id": "#fe4da6b7-b702-4a39-81a6-eed5721056b8",
    "rights": "https://creativecommons.org/publicdomain/zero/1.0/",
    "creator": {
      "id": "https://orcid.org/0000-0002-9499-5840",
      "type": "Person",
      "name": "Timo Homburg",
      "nickname": "situx"
    },
    "generator": {
      "id": "https://github.com/recogito/annotorious-openseadragon",
      "type": "Software",
      "name": "Annotorious-OpenSeadragon 1.5.6",
      "homepage": "https://github.com/recogito/annotorious-openseadragon"
    }
  },
  "#eee58bc6-1cfd-4b33-a8e2-972653589824": {
    "type": "Annotation",
    "body": [
      {
        "type": "TextualBody",
        "purpose": "Transliteration",
        "value": "re",
        "source": "http://purl.org/cuneiform/Transliteration"
      },
      {
        "type": "TextualBody",
        "value": "Character",
        "purpose": "classifying",
        "source": "http://purl.org/cuneiform/Character"
      },
      {
        "type": "TextualBody",
        "purpose": "Charindex",
        "value": "5",
        "source": "http://purl.org/cuneiform/CharacterIndex"
      },
      {
        "type": "TextualBody",
        "purpose": "Line",
        "value": "1",
        "source": "http://purl.org/cuneiform/Line"
      },
      {
        "type": "TextualBody",
        "purpose": "Wordindex",
        "value": "2",
        "source": "http://purl.org/cuneiform/WordIndex"
      },
      {
        "type": "TextualBody",
        "purpose": "RelCharindex",
        "value": "3",
        "source": "http://purl.org/cuneiform/RelativeCharacterIndex"
      },
      {
        "type": "TextualBody",
        "purpose": "linking",
        "value": "http://cdli.ucla.edu/P134535_char_-1_1_5"
      }
    ],
    "target": {
      "source": "https://heidicon.ub.uni-heidelberg.de/iiif/2/1113833:577980/full/full/0/default.jpg",
      "selector": {
        "type": "SvgSelector",
        "value": "<svg><polygon points=\"269.8758544921875,51.88965606689453 439.20001220703125,53.25517272949219 439.20001220703125,159.76551818847656 276.7034606933594,165.2275848388672\"></polygon></svg>"
      },
      "rights": "https://creativecommons.org/licenses/by-sa/4.0/",
      "dimensions": {
        "x": 720,
        "y": 792
      }
    },
    "@context": "http://www.w3.org/ns/anno.jsonld",
    "id": "#eee58bc6-1cfd-4b33-a8e2-972653589824",
    "rights": "https://creativecommons.org/publicdomain/zero/1.0/",
    "creator": {
      "id": "https://orcid.org/0000-0002-9499-5840",
      "type": "Person",
      "name": "Timo Homburg",
      "nickname": "situx"
    },
    "generator": {
      "id": "https://github.com/recogito/annotorious-openseadragon",
      "type": "Software",
      "name": "Annotorious-OpenSeadragon 1.5.6",
      "homepage": "https://github.com/recogito/annotorious-openseadragon"
    }
  },
  "#b12122ab-9fe9-4abf-b4a4-afdb3c6e46bd": {
    "type": "Annotation",
    "body": [
      {
        "type": "TextualBody",
        "purpose": "Transliteration",
        "value": "ta",
        "source": "http://purl.org/cuneiform/Transliteration"
      },
      {
        "type": "TextualBody",
        "value": "Character",
        "purpose": "classifying",
        "source": "http://purl.org/cuneiform/Character"
      },
      {
        "type": "TextualBody",
        "purpose": "Charindex",
        "value": "6",
        "source": "http://purl.org/cuneiform/CharacterIndex"
      },
      {
        "type": "TextualBody",
        "purpose": "Line",
        "value": "1",
        "source": "http://purl.org/cuneiform/Line"
      },
      {
        "type": "TextualBody",
        "purpose": "Wordindex",
        "value": "2",
        "source": "http://purl.org/cuneiform/WordIndex"
      },
      {
        "type": "TextualBody",
        "purpose": "RelCharindex",
        "value": "4",
        "source": "http://purl.org/cuneiform/RelativeCharacterIndex"
      },
      {
        "type": "TextualBody",
        "purpose": "linking",
        "value": "http://cdli.ucla.edu/P134535_char_-1_1_6"
      }
    ],
    "target": {
      "source": "https://heidicon.ub.uni-heidelberg.de/iiif/2/1113833:577980/full/full/0/default.jpg",
      "selector": {
        "type": "SvgSelector",
        "value": "<svg><polygon points=\"441.9310302734375,47.7931022644043 701.3793334960938,49.15862274169922 708.2069091796875,151.57241821289062 444.6620788574219,154.30345153808594\"></polygon></svg>"
      },
      "rights": "https://creativecommons.org/licenses/by-sa/4.0/",
      "dimensions": {
        "x": 720,
        "y": 792
      }
    },
    "@context": "http://www.w3.org/ns/anno.jsonld",
    "id": "#b12122ab-9fe9-4abf-b4a4-afdb3c6e46bd",
    "rights": "https://creativecommons.org/publicdomain/zero/1.0/",
    "creator": {
      "id": "https://orcid.org/0000-0002-9499-5840",
      "type": "Person",
      "name": "Timo Homburg",
      "nickname": "situx"
    },
    "generator": {
      "id": "https://github.com/recogito/annotorious-openseadragon",
      "type": "Software",
      "name": "Annotorious-OpenSeadragon 1.5.6",
      "homepage": "https://github.com/recogito/annotorious-openseadragon"
    }
  },
  "#efabf811-404f-4770-b3e4-ef030bd8ffa6": {
    "type": "Annotation",
    "body": [
      {
        "type": "TextualBody",
        "purpose": "Transliteration",
        "value": "ki",
        "source": "http://purl.org/cuneiform/Transliteration"
      },
      {
        "type": "TextualBody",
        "value": "Character",
        "purpose": "classifying",
        "source": "http://purl.org/cuneiform/Character"
      },
      {
        "type": "TextualBody",
        "purpose": "Line",
        "value": "1",
        "source": "http://purl.org/cuneiform/Line"
      },
      {
        "type": "TextualBody",
        "purpose": "Charindex",
        "value": "1",
        "source": "http://purl.org/cuneiform/CharacterIndex"
      },
      {
        "type": "TextualBody",
        "purpose": "Wordindex",
        "value": "1",
        "source": "http://purl.org/cuneiform/WordIndex"
      },
      {
        "type": "TextualBody",
        "purpose": "RelCharindex",
        "value": "0",
        "source": "http://purl.org/cuneiform/RelativeCharacterIndex"
      },
      {
        "type": "TextualBody",
        "purpose": "linking",
        "value": "http://cdli.ucla.edu/P134535_char_-1_1_1"
      }
    ],
    "target": {
      "source": "https://heidicon.ub.uni-heidelberg.de/iiif/2/1113833:577980/full/full/0/default.jpg",
      "selector": {
        "type": "SvgSelector",
        "value": "<svg><polygon points=\"130.5930938720703,13.655172348022461 7.696547031402588,17.751724243164062 4.965512752532959,101.04827880859375 125.13102722167969,90.12413787841797\"></polygon></svg>"
      },
      "rights": "https://creativecommons.org/licenses/by-sa/4.0/",
      "dimensions": {
        "x": 720,
        "y": 792
      }
    },
    "@context": "http://www.w3.org/ns/anno.jsonld",
    "id": "#efabf811-404f-4770-b3e4-ef030bd8ffa6",
    "rights": "https://creativecommons.org/publicdomain/zero/1.0/",
    "creator": {
      "id": "https://orcid.org/0000-0002-9499-5840",
      "type": "Person",
      "name": "Timo Homburg",
      "nickname": "situx"
    },
    "generator": {
      "id": "https://github.com/recogito/annotorious-openseadragon",
      "type": "Software",
      "name": "Annotorious-OpenSeadragon 1.5.6",
      "homepage": "https://github.com/recogito/annotorious-openseadragon"
    }
  },
  "#229c0bda-954b-4b86-aafa-a15e7f8a2234": {
    "type": "Annotation",
    "body": [
      {
        "type": "TextualBody",
        "purpose": "Transliteration",
        "value": "nanna",
        "source": "http://purl.org/cuneiform/Transliteration"
      },
      {
        "type": "TextualBody",
        "value": "Character",
        "purpose": "classifying",
        "source": "http://purl.org/cuneiform/Character"
      },
      {
        "type": "TextualBody",
        "purpose": "Line",
        "value": "5",
        "source": "http://purl.org/cuneiform/Line"
      },
      {
        "type": "TextualBody",
        "purpose": "Charindex",
        "value": "4",
        "source": "http://purl.org/cuneiform/CharacterIndex"
      },
      {
        "type": "TextualBody",
        "purpose": "linking",
        "value": "http://cdli.ucla.edu/P134535_char_-1_5_4"
      }
    ],
    "target": {
      "source": "https://heidicon.ub.uni-heidelberg.de/iiif/2/1113833:577980/full/full/0/default.jpg",
      "selector": {
        "type": "SvgSelector",
        "value": "<svg><polygon points=\"723.2276000976562,461.5448303222656 545.7103271484375,490.220703125 555.2689819335938,606.2896728515625 716.4000244140625,578.9793090820312\"></polygon></svg>"
      },
      "rights": "https://creativecommons.org/licenses/by-sa/4.0/",
      "dimensions": {
        "x": 720,
        "y": 792
      }
    },
    "@context": "http://www.w3.org/ns/anno.jsonld",
    "id": "#229c0bda-954b-4b86-aafa-a15e7f8a2234",
    "rights": "https://creativecommons.org/publicdomain/zero/1.0/",
    "creator": {
      "id": "https://orcid.org/0000-0002-9499-5840",
      "type": "Person",
      "name": "Timo Homburg",
      "nickname": "situx"
    },
    "generator": {
      "id": "https://github.com/recogito/annotorious-openseadragon",
      "type": "Software",
      "name": "Annotorious-OpenSeadragon 1.5.6",
      "homepage": "https://github.com/recogito/annotorious-openseadragon"
    }
  },
  "#a4520cce-529b-4891-b37a-09968fec9c6b": {
    "type": "Annotation",
    "body": [
      {
        "type": "TextualBody",
        "purpose": "Transliteration",
        "value": "kux(DU)",
        "source": "http://purl.org/cuneiform/Transliteration"
      },
      {
        "type": "TextualBody",
        "value": "Character",
        "purpose": "classifying",
        "source": "http://purl.org/cuneiform/Character"
      },
      {
        "type": "TextualBody",
        "purpose": "Line",
        "value": "2",
        "source": "http://purl.org/cuneiform/Line"
      },
      {
        "type": "TextualBody",
        "purpose": "Charindex",
        "value": "2",
        "source": "http://purl.org/cuneiform/CharacterIndex"
      },
      {
        "type": "TextualBody",
        "purpose": "Wordindex",
        "value": "2",
        "source": "http://purl.org/cuneiform/WordIndex"
      },
      {
        "type": "TextualBody",
        "purpose": "RelCharindex",
        "value": "0",
        "source": "http://purl.org/cuneiform/RelativeCharacterIndex"
      },
      {
        "type": "TextualBody",
        "purpose": "linking",
        "value": "http://cdli.ucla.edu/P134535_char_-1_2_2"
      }
    ],
    "target": {
      "source": "https://heidicon.ub.uni-heidelberg.de/iiif/2/1113833:577980/full/full/0/default.jpg",
      "selector": {
        "type": "SvgSelector",
        "value": "<svg><polygon points=\"642.6620483398438,158.39999389648438 413.25518798828125,162.49655151367188 410.5241394042969,253.9862060546875 631.7379150390625,240.33103942871094\"></polygon></svg>"
      },
      "rights": "https://creativecommons.org/licenses/by-sa/4.0/",
      "dimensions": {
        "x": 720,
        "y": 792
      }
    },
    "@context": "http://www.w3.org/ns/anno.jsonld",
    "id": "#a4520cce-529b-4891-b37a-09968fec9c6b",
    "rights": "https://creativecommons.org/publicdomain/zero/1.0/",
    "creator": {
      "id": "https://orcid.org/0000-0002-9499-5840",
      "type": "Person",
      "name": "Timo Homburg",
      "nickname": "situx"
    },
    "generator": {
      "id": "https://github.com/recogito/annotorious-openseadragon",
      "type": "Software",
      "name": "Annotorious-OpenSeadragon 1.5.6",
      "homepage": "https://github.com/recogito/annotorious-openseadragon"
    }
  },
  "#7d88672e-51c3-4161-9fc6-cbbf6459026a": {
    "type": "Annotation",
    "body": [
      {
        "type": "TextualBody",
        "purpose": "Transliteration",
        "value": "ki",
        "source": "http://purl.org/cuneiform/Transliteration"
      },
      {
        "type": "TextualBody",
        "value": "Character",
        "purpose": "classifying",
        "source": "http://purl.org/cuneiform/Character"
      },
      {
        "type": "TextualBody",
        "purpose": "linking",
        "value": "http://cdli.ucla.edu/P134535_char_-1_-1_-1"
      }
    ],
    "target": {
      "source": "https://heidicon.ub.uni-heidelberg.de/iiif/2/1113833:577980/full/full/0/default.jpg",
      "selector": {
        "type": "SvgSelector",
        "value": "<svg><polygon points=\"14.524133682250977,670.468994140625 112.84137725830078,663.641357421875 116.93792724609375,763.3241577148438 21.35171890258789,767.4207153320312\"></polygon></svg>"
      },
      "rights": "https://creativecommons.org/licenses/by-sa/4.0/",
      "dimensions": {
        "x": 720,
        "y": 792
      }
    },
    "@context": "http://www.w3.org/ns/anno.jsonld",
    "id": "#7d88672e-51c3-4161-9fc6-cbbf6459026a",
    "rights": "https://creativecommons.org/publicdomain/zero/1.0/",
    "creator": {
      "id": "https://orcid.org/0000-0002-9499-5840",
      "type": "Person",
      "name": "Timo Homburg",
      "nickname": "situx"
    },
    "generator": {
      "id": "https://github.com/recogito/annotorious-openseadragon",
      "type": "Software",
      "name": "Annotorious-OpenSeadragon 1.5.6",
      "homepage": "https://github.com/recogito/annotorious-openseadragon"
    }
  },
  "#19f88b88-ffe4-4b90-b7ae-d4260884a31b": {
    "type": "Annotation",
    "body": [
      {
        "type": "TextualBody",
        "purpose": "Transliteration",
        "value": "lugal",
        "source": "http://purl.org/cuneiform/Transliteration"
      },
      {
        "type": "TextualBody",
        "value": "Character",
        "purpose": "tagging",
        "source": "http://purl.org/cuneiform/Character"
      },
      {
        "type": "TextualBody",
        "purpose": "Charindex",
        "value": "2",
        "source": "http://purl.org/cuneiform/CharacterIndex"
      },
      {
        "type": "TextualBody",
        "purpose": "Line",
        "value": "1",
        "source": "http://purl.org/cuneiform/Line"
      },
      {
        "type": "TextualBody",
        "purpose": "Wordindex",
        "value": "1",
        "source": "http://purl.org/cuneiform/WordIndex"
      },
      {
        "type": "TextualBody",
        "purpose": "RelCharindex",
        "value": "1",
        "source": "http://purl.org/cuneiform/RelativeCharacterIndex"
      }
    ],
    "target": {
      "source": "https://heidicon.ub.uni-heidelberg.de/iiif/2/1113833:577980/full/full/0/default.jpg",
      "selector": {
        "type": "SvgSelector",
        "value": "<svg><polygon points=\"404.1180725097656,-0.9655452966690063 131.962890625,15.155144691467285 125.32495880126953,78.68962860107422 412.6525573730469,41.706871032714844\"></polygon></svg>"
      },
      "rights": "https://creativecommons.org/licenses/by-sa/4.0/",
      "dimensions": {
        "x": 720,
        "y": 792
      }
    },
    "@context": "http://www.w3.org/ns/anno.jsonld",
    "id": "#19f88b88-ffe4-4b90-b7ae-d4260884a31b",
    "rights": "https://creativecommons.org/publicdomain/zero/1.0/",
    "creator": {
      "id": "https://orcid.org/0000-0002-9499-5840",
      "type": "Person",
      "name": "Timo Homburg",
      "nickname": "situx"
    },
    "generator": {
      "id": "https://github.com/recogito/annotorious-openseadragon",
      "type": "Software",
      "name": "Annotorious-OpenSeadragon 1.5.6",
      "homepage": "https://github.com/recogito/annotorious-openseadragon"
    }
  },
  "#a2c97e48-4694-4c32-92ca-e7ed18676f69": {
    "type": "Annotation",
    "body": [
      {
        "type": "TextualBody",
        "purpose": "Transliteration",
        "value": "ma2",
        "source": "http://purl.org/cuneiform/Transliteration"
      },
      {
        "type": "TextualBody",
        "value": "Character",
        "purpose": "classifying",
        "source": "http://purl.org/cuneiform/Character"
      },
      {
        "type": "TextualBody",
        "purpose": "Line",
        "value": "1",
        "source": "http://purl.org/cuneiform/Line"
      },
      {
        "type": "TextualBody",
        "purpose": "Charindex",
        "value": "3",
        "source": "http://purl.org/cuneiform/CharacterIndex"
      },
      {
        "type": "TextualBody",
        "purpose": "Wordindex",
        "value": "2",
        "source": "http://purl.org/cuneiform/WordIndex"
      },
      {
        "type": "TextualBody",
        "purpose": "RelCharindex",
        "value": "1",
        "source": "http://purl.org/cuneiform/RelativeCharacterIndex"
      },
      {
        "type": "TextualBody",
        "purpose": "linking",
        "value": "http://cdli.ucla.edu/P134535_char_-1_1_3"
      }
    ],
    "target": {
      "source": "https://heidicon.ub.uni-heidelberg.de/iiif/2/1113833:577980/full/full/0/default.jpg",
      "selector": {
        "type": "SvgSelector",
        "value": "<svg><polygon points=\"508.4284362792969,4.316539287567139 408.8594665527344,3.3682634830474854 410.7560119628906,47.937232971191406 509.376708984375,49.83378219604492\"></polygon></svg>"
      },
      "rights": "https://creativecommons.org/licenses/by-sa/4.0/",
      "dimensions": {
        "x": 720,
        "y": 792
      }
    },
    "@context": "http://www.w3.org/ns/anno.jsonld",
    "id": "#a2c97e48-4694-4c32-92ca-e7ed18676f69",
    "rights": "https://creativecommons.org/publicdomain/zero/1.0/",
    "creator": {
      "id": "https://orcid.org/0000-0002-9499-5840",
      "type": "Person",
      "name": "Timo Homburg",
      "nickname": "situx"
    },
    "generator": {
      "id": "https://github.com/recogito/annotorious-openseadragon",
      "type": "Software",
      "name": "Annotorious-OpenSeadragon 1.5.6",
      "homepage": "https://github.com/recogito/annotorious-openseadragon"
    }
  },
  "#ef6f0819-2f6f-4259-9da6-07ff1284b9c1": {
    "type": "Annotation",
    "body": [
      {
        "type": "TextualBody",
        "purpose": "Transliteration",
        "value": "gur8",
        "source": "http://purl.org/cuneiform/Transliteration"
      },
      {
        "type": "TextualBody",
        "value": "Character",
        "purpose": "classifying",
        "source": "http://purl.org/cuneiform/Character"
      },
      {
        "type": "TextualBody",
        "purpose": "Charindex",
        "value": "4",
        "source": "http://purl.org/cuneiform/CharacterIndex"
      },
      {
        "type": "TextualBody",
        "purpose": "Line",
        "value": "1",
        "source": "http://purl.org/cuneiform/Line"
      },
      {
        "type": "TextualBody",
        "purpose": "Wordindex",
        "value": "2",
        "source": "http://purl.org/cuneiform/WordIndex"
      },
      {
        "type": "TextualBody",
        "purpose": "RelCharindex",
        "value": "2",
        "source": "http://purl.org/cuneiform/RelativeCharacterIndex"
      },
      {
        "type": "TextualBody",
        "purpose": "linking",
        "value": "http://cdli.ucla.edu/P134535_char_-1_1_4"
      }
    ],
    "target": {
      "source": "https://heidicon.ub.uni-heidelberg.de/iiif/2/1113833:577980/full/full/0/default.jpg",
      "selector": {
        "type": "SvgSelector",
        "value": "<svg><polygon points=\"692.3939208984375,15.695850372314453 552.0491333007812,6.2130913734436035 555.8422241210938,47.937232971191406 693.3422241210938,47.937232971191406\"></polygon></svg>"
      },
      "rights": "https://creativecommons.org/licenses/by-sa/4.0/",
      "dimensions": {
        "x": 720,
        "y": 792
      }
    },
    "@context": "http://www.w3.org/ns/anno.jsonld",
    "id": "#ef6f0819-2f6f-4259-9da6-07ff1284b9c1",
    "rights": "https://creativecommons.org/publicdomain/zero/1.0/",
    "creator": {
      "id": "https://orcid.org/0000-0002-9499-5840",
      "type": "Person",
      "name": "Timo Homburg",
      "nickname": "situx"
    },
    "generator": {
      "id": "https://github.com/recogito/annotorious-openseadragon",
      "type": "Software",
      "name": "Annotorious-OpenSeadragon 1.5.6",
      "homepage": "https://github.com/recogito/annotorious-openseadragon"
    }
  },
  "#2fe0e5a0-cad8-4cc3-8f1b-52cf043fc975": {
    "type": "Annotation",
    "body": [
      {
        "type": "TextualBody",
        "purpose": "Transliteration",
        "value": "d",
        "source": "http://purl.org/cuneiform/Transliteration"
      },
      {
        "type": "TextualBody",
        "value": "Character",
        "purpose": "classifying",
        "source": "http://purl.org/cuneiform/Character"
      },
      {
        "type": "TextualBody",
        "purpose": "linking",
        "value": "http://cdli.ucla.edu/P134535_char_-1_-1_-1"
      }
    ],
    "target": {
      "source": "https://heidicon.ub.uni-heidelberg.de/iiif/2/1113833:577980/full/full/0/default.jpg",
      "selector": {
        "type": "SvgSelector",
        "value": "<svg><polygon points=\"549.806884765625,618.5792846679688 474.7034606933594,621.3103637695312 478.79998779296875,680.027587890625 560.7310180664062,673.2000122070312\"></polygon></svg>"
      },
      "rights": "https://creativecommons.org/licenses/by-sa/4.0/"
    },
    "@context": "http://www.w3.org/ns/anno.jsonld",
    "id": "#2fe0e5a0-cad8-4cc3-8f1b-52cf043fc975",
    "rights": "https://creativecommons.org/publicdomain/zero/1.0/",
    "creator": {
      "id": "https://orcid.org/0000-0002-9499-5840",
      "type": "Person",
      "name": "Timo Homburg",
      "nickname": "situx"
    },
    "generator": {
      "id": "https://github.com/recogito/annotorious-openseadragon",
      "type": "Software",
      "name": "Annotorious-OpenSeadragon 1.5.6",
      "homepage": "https://github.com/recogito/annotorious-openseadragon"
    }
  },
  "#9d5e4d98-e0bf-4304-9790-3fb59c6aa2b0": {
    "type": "Annotation",
    "body": [
      {
        "type": "TextualBody",
        "purpose": "Transliteration",
        "value": "suen",
        "source": "http://purl.org/cuneiform/Transliteration"
      },
      {
        "type": "TextualBody",
        "value": "Character",
        "purpose": "classifying",
        "source": "http://purl.org/cuneiform/Character"
      },
      {
        "type": "TextualBody",
        "purpose": "linking",
        "value": "http://cdli.ucla.edu/P134535_char_-1_-1_-1"
      }
    ],
    "target": {
      "source": "https://heidicon.ub.uni-heidelberg.de/iiif/2/1113833:577980/full/full/0/default.jpg",
      "selector": {
        "type": "SvgSelector",
        "value": "<svg><polygon points=\"458.3172302246094,677.2965698242188 465.14483642578125,734.6482543945312 462.4137878417969,734.6482543945312 717.7655029296875,707.3379516601562 719.1310424804688,574.8827514648438 555.2689819335938,596.7310180664062 566.193115234375,674.5654907226562 564.8275756835938,674.5654907226562\"></polygon></svg>"
      },
      "rights": "https://creativecommons.org/licenses/by-sa/4.0/",
      "dimensions": {
        "x": 720,
        "y": 792
      }
    },
    "@context": "http://www.w3.org/ns/anno.jsonld",
    "id": "#9d5e4d98-e0bf-4304-9790-3fb59c6aa2b0",
    "rights": "https://creativecommons.org/publicdomain/zero/1.0/",
    "creator": {
      "id": "https://orcid.org/0000-0002-9499-5840",
      "type": "Person",
      "name": "Timo Homburg",
      "nickname": "situx"
    },
    "generator": {
      "id": "https://github.com/recogito/annotorious-openseadragon",
      "type": "Software",
      "name": "Annotorious-OpenSeadragon 1.5.6",
      "homepage": "https://github.com/recogito/annotorious-openseadragon"
    }
  }
}